pypomod/__init__.py
pypomod/main.py
pypomod/pomodoro.py
pypomod/tools.py
pypomod-0.1.0.dist-info/entry_points.txt
pypomod-0.1.0.dist-info/WHEEL
pypomod-0.1.0.dist-info/METADATA
pypomod-0.1.0.dist-info/RECORD
