Metadata-Version: 2.1
Name: pypomod
Version: 0.1.0
Summary: Simple Python CLI package for Pomodoro timer.
Author: Kyoungseoun Chung
Author-email: kyoungseoun.chung@gmail.com
Requires-Python: >=3.10,<4.0
Classifier: Programming Language :: Python :: 3
Classifier: Programming Language :: Python :: 3.10
